odoo8_addon_web_widget_one2many_tags-8.0.1.0.0.99.dev26-py2.7-nspkg.pth
odoo8_addon_web_widget_one2many_tags-8.0.1.0.0.99.dev26.dist-info/DESCRIPTION.rst
odoo8_addon_web_widget_one2many_tags-8.0.1.0.0.99.dev26.dist-info/METADATA
odoo8_addon_web_widget_one2many_tags-8.0.1.0.0.99.dev26.dist-info/RECORD
odoo8_addon_web_widget_one2many_tags-8.0.1.0.0.99.dev26.dist-info/WHEEL
odoo8_addon_web_widget_one2many_tags-8.0.1.0.0.99.dev26.dist-info/metadata.json
odoo8_addon_web_widget_one2many_tags-8.0.1.0.0.99.dev26.dist-info/namespace_packages.txt
odoo8_addon_web_widget_one2many_tags-8.0.1.0.0.99.dev26.dist-info/top_level.txt
odoo_addons/web_widget_one2many_tags/README.rst
odoo_addons/web_widget_one2many_tags/__init__.py
odoo_addons/web_widget_one2many_tags/__openerp__.py
odoo_addons/web_widget_one2many_tags/i18n/es.po
odoo_addons/web_widget_one2many_tags/i18n/fi.po
odoo_addons/web_widget_one2many_tags/i18n/fr.po
odoo_addons/web_widget_one2many_tags/i18n/it.po
odoo_addons/web_widget_one2many_tags/i18n/nl.po
odoo_addons/web_widget_one2many_tags/i18n/sl.po
odoo_addons/web_widget_one2many_tags/i18n/tr.po
odoo_addons/web_widget_one2many_tags/i18n/web_widget_one2many_tags.pot
odoo_addons/web_widget_one2many_tags/static/description/icon.png
odoo_addons/web_widget_one2many_tags/static/src/js/web_widget_one2many_tags.js
odoo_addons/web_widget_one2many_tags/static/src/xml/web_widget_one2many_tags.xml
odoo_addons/web_widget_one2many_tags/views/templates.xml
